duplicity/__init__.py
duplicity/__main__.py
duplicity/_librsync.cpython-312-x86_64-linux-gnu.so
duplicity/_librsyncmodule.c
duplicity/argparse311.py
duplicity/backend.py
duplicity/backend_pool.py
duplicity/cached_ops.py
duplicity/cli_data.py
duplicity/cli_main.py
duplicity/cli_util.py
duplicity/config.py
duplicity/diffdir.py
duplicity/dup_collections.py
duplicity/dup_main.py
duplicity/dup_tarfile.py
duplicity/dup_temp.py
duplicity/dup_time.py
duplicity/errors.py
duplicity/file_naming.py
duplicity/filechunkio.py
duplicity/globmatch.py
duplicity/gpg.py
duplicity/gpginterface.py
duplicity/lazy.py
duplicity/librsync.py
duplicity/log.py
duplicity/manifest.py
duplicity/patchdir.py
duplicity/path.py
duplicity/progress.py
duplicity/robust.py
duplicity/selection.py
duplicity/statistics.py
duplicity/tempdir.py
duplicity/util.py
duplicity/backends/__init__.py
duplicity/backends/_cf_cloudfiles.py
duplicity/backends/_cf_pyrax.py
duplicity/backends/_testbackend.py
duplicity/backends/adbackend.py
duplicity/backends/azurebackend.py
duplicity/backends/b2backend.py
duplicity/backends/boxbackend.py
duplicity/backends/cfbackend.py
duplicity/backends/dpbxbackend.py
duplicity/backends/gdocsbackend.py
duplicity/backends/gdrivebackend.py
duplicity/backends/giobackend.py
duplicity/backends/hsibackend.py
duplicity/backends/hubicbackend.py
duplicity/backends/idrivedbackend.py
duplicity/backends/imapbackend.py
duplicity/backends/jottacloudbackend.py
duplicity/backends/lftpbackend.py
duplicity/backends/localbackend.py
duplicity/backends/mediafirebackend.py
duplicity/backends/megabackend.py
duplicity/backends/megav2backend.py
duplicity/backends/megav3backend.py
duplicity/backends/multibackend.py
duplicity/backends/ncftpbackend.py
duplicity/backends/onedrivebackend.py
duplicity/backends/par2backend.py
duplicity/backends/pcabackend.py
duplicity/backends/pydrivebackend.py
duplicity/backends/rclonebackend.py
duplicity-3.0.7.dist-info/METADATA
duplicity-3.0.7.dist-info/WHEEL
duplicity-3.0.7.dist-info/entry_points.txt
duplicity-3.0.7.dist-info/top_level.txt
duplicity-3.0.7.dist-info/RECORD
duplicity-3.0.7.dist-info/licenses/AUTHORS.md
duplicity-3.0.7.dist-info/licenses/COPYING
duplicity-3.0.7.dist-info/sboms/auditwheel.cdx.json
