Metadata-Version: 2.4
Name: duplicity
Version: 3.0.7
Summary: Encrypted backup using rsync algorithm
Author-email: Kenneth Loafman <kenneth@loafman.com>
Maintainer: Edgar Soldin, Thomas Laubrock
Project-URL: Homepage, http://duplicity.us
Project-URL: Download, https://gitlab.com/duplicity/duplicity/-/releases
Project-URL: Issues, https://gitlab.com/duplicity/duplicity/-/issues
Project-URL: Contact, https://lists.nongnu.org/mailman/listinfo/duplicity-talk
Project-URL: Documentation, http://duplicity.us
Project-URL: Repository, https://gitlab.com/duplicity/duplicity
Project-URL: Changelog, https://gitlab.com/duplicity/duplicity/-/blob/main/CHANGELOG.md
Platform: any
Classifier: Development Status :: 6 - Mature
Classifier: Environment :: Console
Classifier: Operating System :: MacOS
Classifier: Operating System :: POSIX
Classifier: Programming Language :: C
Classifier: Programming Language :: Python :: 3
Classifier: Programming Language :: Python :: 3.9
Classifier: Programming Language :: Python :: 3.10
Classifier: Programming Language :: Python :: 3.11
Classifier: Programming Language :: Python :: 3.12
Classifier: Programming Language :: Python :: 3.13
Classifier: Programming Language :: Python :: 3.14
Classifier: Topic :: System :: Archiving :: Backup
Requires-Python: <3.15,>3.8
License-File: COPYING
License-File: AUTHORS.md
Requires-Dist: fasteners>=0.19
Requires-Dist: python-gettext>=5.0
Requires-Dist: setuptools>=78.1.0
Requires-Dist: azure-storage-blob
Requires-Dist: b2sdk
Requires-Dist: boto3
Requires-Dist: botocore
Requires-Dist: boxsdk[jwt]
Requires-Dist: dropbox
Requires-Dist: gdata-python3
Requires-Dist: google-api-python-client
Requires-Dist: google-auth-oauthlib
Requires-Dist: httplib2
Requires-Dist: pysocks
Requires-Dist: jottalib
Requires-Dist: keyring
Requires-Dist: lxml<=5.4.0
Requires-Dist: mediafire
Requires-Dist: megatools
Requires-Dist: paramiko
Requires-Dist: pexpect
Requires-Dist: psutil
Requires-Dist: pydrive2
Requires-Dist: pyrax
Requires-Dist: python-swiftclient
Requires-Dist: requests
Requires-Dist: requests-oauthlib
Dynamic: license-file
